dyndns/__init__.py
dyndns/cli.py
dyndns/config.py
dyndns/dns.py
dyndns/environment.py
dyndns/exceptions.py
dyndns/ipaddresses.py
dyndns/log.py
dyndns/names.py
dyndns/webapp.py
dyndns/wsgi.py
dyndns/zones.py
dyndns-2.0.0.dist-info/LICENSE
dyndns-2.0.0.dist-info/METADATA
dyndns-2.0.0.dist-info/WHEEL
dyndns-2.0.0.dist-info/entry_points.txt
dyndns-2.0.0.dist-info/RECORD
