Metadata-Version: 2.1
Name: dyndns
Version: 2.0.0
Summary: A simple dynamic DNS HTTP based update API using Python and the Flask web framework.
Home-page: https://github.com/Josef-Friedrich/dyndns
License: MIT
Author: Josef Friedrich
Author-email: josef@friedrich.rocks
Requires-Python: >=3.10,<4.0
Classifier: License :: OSI Approved :: MIT License
Classifier: Operating System :: OS Independent
Classifier: Programming Language :: Python :: 3
Classifier: Programming Language :: Python :: 3.10
Classifier: Programming Language :: Python :: 3.11
Classifier: Programming Language :: Python :: 3.12
Requires-Dist: Flask (>=3,<4)
Requires-Dist: PyYAML (>=6,<7)
Requires-Dist: dnspython (>=2,<3)
Requires-Dist: pydantic (>=2,<3)
Requires-Dist: types-PyYAML
Requires-Dist: typing-extensions (>=4,<5)
Project-URL: Repository, https://github.com/Josef-Friedrich/dyndns
